Workbook
Name SolutionProfiles: '_Lists'!$A$2:$A$5
Name StudyTypes: _Lists!$B$2:$B$20
Name CostItemKind: '_Lists'!$C$2:$C$6
Name BenefitCategory: '_Lists'!$D$2:$D$9
Name FunctionKind: '_Lists'!$E$2:$E$3
Name RecommendationStatus: '_Lists'!$F$2:$F$6
Name YesNo: '_Lists'!$G$2:$G$3
Name Currencies: '_Lists'!$H$2:$H$9
Name KpiNames: '_Lists'!$I$2:$I$31
Name WorkPackageStatus: '_Lists'!$J$2:$J$5
Name RiskStatus: '_Lists'!$K$2:$K$5
Name Health: '_Lists'!$L$2:$L$4
Name Confidence: '_Lists'!$M$2:$M$4
Name Scale: '_Lists'!$N$2:$N$6
Name TrackOrigin: '_Lists'!$O$2:$O$3
Name ArtifactType: '_Lists'!$P$2:$P$6
Name LessonCat: '_Lists'!$Q$2:$Q$4

Sheet Read me
A1: Value Lifecycle · VE Discovery Workbook — Read me
A2: How to use this workbook, and how each tab maps to the Value Lifecycle Platform.
A5: Purpose | B5: Capture what you learn in client meetings, then transcribe into the app — or import this whole file.
A6: Colour key | B6: Yellow cells = you fill in. Grey cells = auto-calculated (don't type over them). Header rows = fixed.
A7: Dropdowns | B7: Cells with a dropdown use the app's own pick-lists (solution profiles, study types, KPIs, currencies, statuses) so entries match the system.
A8: Example row | B8: The first data row of each table is a greyed-italic EXAMPLE of the format — overwrite it or delete it.
A9: Provenance | B9: Wherever you record a number, capture its Source / Period / Assumption / Confidence.
A10: Importing | B10: A study/track can be loaded straight from this file: npx tsx scripts/import-workbook.ts <file>.xlsx (add --dry-run to preview).
A11: Before you import | B11: Delete the greyed example row in each table (or add rows beneath it); keep the tab names and column headers unchanged.
A13: Tab → App module
A14: 1. Engagement | B14: New VE study header
A15: 2. Orientation | B15: Problem, scope, stakeholders, value hypothesis
A16: 3. Baseline | B16: Current-state cost & pain (with sources)
A17: 4. Functions | B17: Function analysis — verb/noun, cost, worth
A18: 5. Alternatives | B18: Creative alternatives (linked to functions)
A19: 6. Evaluation | B19: Evaluation matrix — criteria, weights, scores
A20: 7. Recommendations | B20: Developed recommendations
A21: 8. Business case | B21: Cost/benefit line items + ROI/payback/NPV
A22: 9. Handover pack | B22: KPIs, baselines, success criteria, expected benefits
A23: 10. Risks | B23: Study risk register
A24: Reference | B24: KPI catalogue + per-profile drivers & levers

Sheet Reference
A1: Reference — KPI catalogue & profile prompts
A2: Pick-list prompts from the app. Use these to fill the dropdowns and shape the conversation.
A4: KPI key | B4: KPI name | C4: Unit | D4: Direction | E4: Discipline | F4: Category
A5: cost_savings | B5: Estimated / realized cost savings | C5: USD | D5: HIGHER_IS_BETTER | E5: VE | F5: COST_SAVING
A6: roi_pct | B6: Return on investment | C6: % | D6: HIGHER_IS_BETTER | E6: VE | F6: COST_SAVING
A7: payback_period | B7: Payback period | C7: months | D7: LOWER_IS_BETTER | E7: VE | F7: COST_SAVING
A8: revenue_uplift | B8: Revenue uplift | C8: USD | D8: HIGHER_IS_BETTER | E8: VR | F8: REVENUE_UPLIFT
A9: alternatives_generated | B9: Alternatives generated | C9: count | D9: HIGHER_IS_BETTER | E9: VE | F9: OTHER
A10: recommendations_accepted | B10: Recommendations accepted | C10: count | D10: HIGHER_IS_BETTER | E10: VE | F10: OTHER
A11: study_cycle_time | B11: Study cycle time | C11: days | D11: LOWER_IS_BETTER | E11: VE | F11: TIME_SAVING
A12: avg_roi | B12: Average ROI per study | C12: % | D12: HIGHER_IS_BETTER | E12: VE | F12: COST_SAVING
A13: on_time_implementation | B13: On-time implementation | C13: % | D13: HIGHER_IS_BETTER | E13: VR | F13: SCHEDULE
A14: adoption_rate | B14: Adoption rate | C14: % | D14: HIGHER_IS_BETTER | E14: VR | F14: OTHER
A15: task_utilization | B15: Licence / capacity utilization | C15: % | D15: HIGHER_IS_BETTER | E15: VR | F15: COST_SAVING
... A34: first_contact_resolution | B34: First-contact resolution | C34: % | D34: HIGHER_IS_BETTER | E34: VR | F34: QUALITY

Sheet _Lists
A1: SolutionProfiles | B1: StudyTypes | C1: CostItemKind | D1: BenefitCategory | E1: FunctionKind | F1: RecommendationStatus | G1: YesNo | H1: Currencies | I1: KpiNames | J1: WorkPackageStatus | K1: RiskStatus | L1: Health | M1: Confidence | N1: Scale | O1: TrackOrigin | P1: ArtifactType | Q1: LessonCat
A2: automation | B2: Adoption & value-realization study | C2: CAPEX | D2: COST_SAVING | E2: BASIC | F2: PROPOSED | G2: Yes | H2: USD | I2: Estimated / realized cost savings | J2: NOT_STARTED | K2: OPEN | L2: GREEN | M2: High | N2: 1 | O2: STANDALONE (existing software) | P2: EXPECTED_BENEFIT | Q2: what_worked
A3: mainframe | B3: Automation value study | C3: OPEX | D3: REVENUE_UPLIFT | E3: SECONDARY | F3: SHORTLISTED | G3: No | H3: ZAR | I3: Return on investment | J3: IN_PROGRESS | K3: MITIGATING | L3: AMBER | M3: Medium | N3: 2 | O3: VE_HANDOVER (from a study) | P3: SUCCESS_CRITERION | Q3: what_to_change
A4: serviceops | B4: Availability & resilience review | C4: ONE_OFF | D4: RISK_REDUCTION | F4: ACCEPTED | H4: EUR | I4: Payback period | J4: BLOCKED | K4: CLOSED | L4: RED | M4: Low | N4: 3 | P4: BASELINE | Q4: recommendation_for_ve
A5: reseller | B5: Build-vs-buy business case | C5: RECURRING | D5: TIME_SAVING | F5: REJECTED | H5: GBP | I5: Revenue uplift | J5: DONE | K5: ACCEPTED | N5: 4 | P5: KPI
B6: Capacity & cost forecasting study | C6: BENEFIT | D6: QUALITY | F6: DEFERRED | H6: AUD | I6: Alternatives generated | N6: 5 | P6: RISK
B7: Cloud migration / modernization TCO case | D7: SCHEDULE | H7: NGN | I7: Recommendations accepted
B8: Competitive displacement / TCO case | D8: RELIABILITY | H8: KES | I8: Study cycle time
B9: Consolidation case (tool / licence) | D9: OTHER | H9: BWP | I9: Average ROI per study
B10: Continuous optimization / cost case | I10: On-time implementation
B11: Cost-optimization study | I11: Adoption rate
B12: ITSM value / TCO study | I12: Licence / capacity utilization
B13: Managed-service (MSP) migration case | I13: Time-to-value
B14: Proof-of-value (PoV) outcome study | I14: Developer productivity
B15: Renewal & expansion case | I15: New-developer onboarding time
B16: ROI / TCO business case | I16: Realized value
B17: SaaS migration case | I17: Planned vs realized variance
B18: Security & compliance risk-reduction case | I18: Value reports / QBRs delivered
B19: Self-service deflection study | I19: Total realized value (portfolio)
B20: Value realisation & optimisation study | I20: Template / plan reuse rate
I21: Schedule impact
I22: Life-cycle cost reduction
I23: Reliability / uptime
I24: Unit cost reduction
I25: First pass yield
I26: Mainframe cost reduction (MLC / MSU)
I27: Mean time to resolve (MTTR)
I28: Job success rate
I29: SLA attainment
I30: Ticket deflection rate
I31: First-contact resolution

Sheet 1. Engagement
A1: 1 · Engagement
A2: New VE study header → maps to the app's New VE Study form.
A4: Client / account
A5: Opportunity name
A6: Solution profile | B6: serviceops
A7: Study type | B7: Managed multi-tenant ITSM migration (incumbent displacement)
A8: Study title (as it will appear in app) | B8: Managed multi-tenant ITSM migration — incumbent displacement (MSP)
A9: Value Engineer (owner)
A10: Currency | B10: USD
A11: Estimated value (optional) | B11: 600000
A12: Meeting date(s)
A13: Target decision date | B13: 2026-12-15

Sheet 2. Orientation
A1: 2 · Orientation
A2: Problem, scope, stakeholders, value hypothesis.
A4: Problem statement (1–2 lines) | B4: A managed service provider (MSP) runs its service desk on a self-hosted, mid-market incumbent ITSM tool that it administers itself. As the estate scales across many client relationships, the platform's automation, multi-tenant governance and self-service depth limit analyst productivity and SLA consistency, and platform operations consume internal capacity that could be billable. The MSP wants to move to a ring-fenced, multi-tenant, enterprise-grade ITSM platform on a partner's managed cloud — run and managed by the platform partner.
A5: Scope — IN | B5: Migration of the MSP's managed-services ITSM off the incumbent to a ring-fenced, multi-tenant platform on the partner's managed cloud: incident, request, change, problem, knowledge; self-service portal; digital workplace + GenAI virtual agent; tenant onboarding & data isolation; core integrations (directory/SSO, email, monitoring); partner-managed run & operate.
A6: Scope — OUT | B6: AIOps and Discovery/CMDB (planned as a later phase — see recommendations); the MSP's non-ITSM applications; end-customer business-process change; the partner's shared multi-tenant offering (this is a separate ring-fenced instance).
A7: Target value outcome
A8: Value hypothesis (rough size & driver) | B8: ~$0.6M/yr net value: offloading platform operations to the partner, lifting analyst productivity with platform automation + GenAI self-service deflection, protecting SLA-linked managed-services revenue, and enabling multi-tenant scale — against a higher but fully-managed recurring cost and a one-off migration. Payback ~8 months.
A10: Stakeholders
A11: Name | B11: Role / title | C11: Economic buyer? | D11: Owns which numbers | E11: Notes
A12: CIO / Managed Services Exec (MSP) | B12: Economic buyer | C12: Yes | D12: Managed-services P&L & platform budget | E12: Sponsor; wants scale, differentiation and predictable, managed platform cost
A13: Head of Service Management (MSP) | B13: Service owner | C13: No | D13: SLA attainment, ticket volumes, CSAT | E13: Owns managed-services delivery outcomes across tenants
A14: Platform / Tooling Lead (MSP) | B14: Operations | C14: No | D14: Incumbent admin, hosting, integrations | E14: Self-manages the incumbent today; platform ops to be offloaded to the partner
A15: Procurement / Vendor Management (MSP) | B15: Procurement | C15: No | D15: Licensing & vendor contracts | E15: Wants predictable, value-justified spend
A16: Client SLA / Commercial Lead (MSP) | B16: Commercial | C16: No | D16: Managed-services contracts & SLA credits | E16: Cares about SLA-linked revenue protection
A17: Account Executive (platform partner) | B17: Platform partner | C17: No | D17: MSP account & managed platform offering | E17: Owns the partner relationship and the managed-platform commercial
A18: Delivery Lead (platform partner) | B18: Platform partner | C18: No | D18: Migration & managed-service delivery | E18: Builds the ring-fenced instance and runs the ongoing managed service

Sheet 3. Baseline
A1: 3 · Current-state baseline
A2: Information phase. Capture the number AND where it came from.
A4: Item / metric | B4: Current value | C4: Unit | D4: Source | E4: Period | F4: Assumption | G4: Confidence
A5: Service-desk agents / technicians on platform | B5: 250 | C5: agents | D5: MSP estimate | E5: 2026 | F5: Managed-services delivery | G5: Medium
A6: End-customer tenants served (initial) | B6: 40 | C6: tenants | D6: MSP estimate | E6: 2026 | F6: Multi-tenant managed services | G6: Medium
A7: Incumbent ITSM subscription (self-hosted mid-market tool) | B7: 180000 | C7: USD/yr | D7: Contract | E7: FY2026 | F7: Technician-based | G7: High
A8: Self-hosting + platform administration (infra + ~3 FTE) | B8: 320000 | C8: USD/yr | D8: MSP estimate | E8: FY2026 | F8: MSP runs the platform today | G8: Medium
A9: Self-service deflection | B9: 12 | C9: % | D9: Portal analytics | E9: 2026 | F9: Low; limited self-service | G9: Medium
A10: SLA attainment (across managed tenants) | B10: 90 | C10: % | D10: Service reports | E10: Q2 2026 | F10: Blended across contracts | G10: Medium
A11: Mean time to resolve (MTTR) | B11: 7.5 | C11: hours | D11: ITSM reports | E11: Q2 2026 | F11: P2/P3 blended | G11: Medium
A12: Manual / repetitive ticket effort | B12: 35 | C12: % | D12: Ops estimate | E12: 2026 | F12: Automatable on the new platform | G12: Low
A13: Tenant onboarding time (new client) | B13: 6 | C13: weeks | D13: Ops estimate | E13: 2026 | F13: Manual setup on the incumbent | G13: Medium
A14: Platform automation maturity | B14: Low | C14: status | D14: Discovery | E14: 2026 | F14: Limited workflow automation | G14: Medium
A15: Deployment / operating model | B15: Self-managed | C15: status | D15: Discovery | E15: 2026 | F15: MSP self-hosts & administers the incumbent | G15: High

Sheet 4. Functions
A1: 4 · Function analysis
A2: Verb + noun. Value index = worth ÷ cost (auto).
A4: Verb | B4: Noun | C4: Kind | D4: Cost | E4: Worth | F4: Value index (auto) | G4: Supports (why) →
A5: Resolve | B5: Incidents | C5: BASIC | D5: 520000 | E5: 620000 | F5: =IFERROR(E5/D5,"")
A6: Fulfil | B6: Requests | C6: BASIC | D6: 300000 | E6: 340000 | F6: =IFERROR(E6/D6,"")
A7: Isolate | B7: Tenants | C7: BASIC | D7: 260000 | E7: 420000 | F7: =IFERROR(E7/D7,"")
A8: Deflect | B8: Contacts | C8: SECONDARY | D8: 140000 | E8: 320000 | F8: =IFERROR(E8/D8,"")
A9: Automate | B9: Workflows | C9: SECONDARY | D9: 180000 | E9: 350000 | F9: =IFERROR(E9/D9,"")
A10: Operate | B10: Platform | C10: SECONDARY | D10: 420000 | E10: 200000 | F10: =IFERROR(E10/D10,"")
A11: License | B11: Technicians | C11: SECONDARY | D11: 180000 | E11: 170000 | F11: =IFERROR(E11/D11,"")
F12: =IFERROR(E12/D12,"")
F13: =IFERROR(E13/D13,"")
F14: =IFERROR(E14/D14,"")
F15: =IFERROR(E15/D15,"")
F16: =IFERROR(E16/D16,"")
F17: =IFERROR(E17/D17,"")
F18: =IFERROR(E18/D18,"")
F19: =IFERROR(E19/D19,"")
F20: =IFERROR(E20/D20,"")

Sheet 5. Alternatives
A1: 5 · Creative alternatives
A2: Ideas for the high-value functions. Shortlist the ones worth evaluating.
A4: Idea | B4: Linked function (verb+noun) | C4: Description | D4: Rough value | E4: Shortlisted?
A5: Migrate to the partner-managed multi-tenant ITSM platform (ring-fenced) | B5: Operate Platform | C5: Move ITSM to a ring-fenced multi-tenant platform on the partner's managed cloud; partner runs & manages it | D5: 600000 | E5: Yes
A6: Add a GenAI self-service virtual agent | B6: Deflect Contacts | C6: GenAI self-service to deflect contacts and speed resolution | D6: 230000 | E6: Yes
A7: Phase 2 — add AIOps and Discovery/CMDB | B7: Automate Workflows | C7: Event correlation, MTTR reduction and CMDB accuracy across tenants (planned expansion) | D7: 230000 | E7: Yes
A8: Stay on the incumbent, self-hosted (status quo) | B8: License Technicians | C8: Keep the incumbent; renegotiate; no platform-ops offload | D8: 0 | E8: No
A9: Upgrade the incumbent + build automation in-house | B9: Automate Workflows | C9: Extend the incumbent and self-manage more automation | D9: 120000 | E9: No

Sheet 6. Evaluation
A1: 6 · Evaluation matrix
A2: Weight the criteria (total 100%), score each alternative 1–5 (auto-weighted).
A4: Criteria & weights
A5: Criterion | B5: Weight %
A6: Cost impact | B6: 30
A7: Performance | B7: 25
A8: Risk | B8: 20
A9: Feasibility | B9: 15
A10: Schedule | B10: 10
A11: Total | B11: =SUM(B6:B10)
A13: Score each alternative (1–5)
A14: Alternative | B14: Cost impact | C14: Performance | D14: Risk | E14: Feasibility | F14: Schedule | G14: Weighted score (auto)
A15: Migrate to the partner-managed multi-tenant ITSM platform (ring-fenced) | B15: 4 | C15: 5 | D15: 4 | E15: 4 | F15: 4 | G15: =IF(COUNT(B15:F15)=0,"",B15*$B$6+C15*$B$7+D15*$B$8+E15*$B$9+F15*$B$10)
A16: Add a GenAI self-service virtual agent | B16: 4 | C16: 5 | D16: 4 | E16: 4 | F16: 4 | G16: =IF(COUNT(B16:F16)=0,"",B16*$B$6+C16*$B$7+D16*$B$8+E16*$B$9+F16*$B$10)
A17: Phase 2 — add AIOps and Discovery/CMDB | B17: 3 | C17: 5 | D17: 3 | E17: 3 | F17: 2 | G17: =IF(COUNT(B17:F17)=0,"",B17*$B$6+C17*$B$7+D17*$B$8+E17*$B$9+F17*$B$10)
G18: =IF(COUNT(B18:F18)=0,"",B18*$B$6+C18*$B$7+D18*$B$8+E18*$B$9+F18*$B$10)
G19: =IF(COUNT(B19:F19)=0,"",B19*$B$6+C19*$B$7+D19*$B$8+E19*$B$9+F19*$B$10)
G20: =IF(COUNT(B20:F20)=0,"",B20*$B$6+C20*$B$7+D20*$B$8+E20*$B$9+F20*$B$10)
G21: =IF(COUNT(B21:F21)=0,"",B21*$B$6+C21*$B$7+D21*$B$8+E21*$B$9+F21*$B$10)
G22: =IF(COUNT(B22:F22)=0,"",B22*$B$6+C22*$B$7+D22*$B$8+E22*$B$9+F22*$B$10)

Sheet 7. Recommendations
A1: 7 · Recommendations
A2: Developed recs. Status ACCEPTED is the guard for handover.
A4: Title | B4: Summary | C4: Technical detail | D4: Commercial detail | E4: Est. value | F4: Est. cost | G4: Status
A5: Migrate the MSP's managed-services ITSM to the partner-managed platform | B5: Displace the self-hosted incumbent with a ring-fenced, multi-tenant ITSM platform on the partner's managed cloud, run and managed by the partner. | C5: Ring-fenced multi-tenant ITSM (isolated from the partner's shared offering); incident/request/change/problem/knowledge; self-service portal; digital workplace + GenAI virtual agent; per-tenant data isolation, SLAs & dashboards; directory/SSO, email & monitoring integrations; partner patches, upgrades and operates the platform. | D5: Recurring platform subscription + partner managed-service fee (opex) replaces the incumbent licence + self-hosting/admin; one-off migration & onboarding services. Net ~$0.6M/yr; payback ~8 months. | E5: 600000 | F5: 420000 | G5: ACCEPTED
A6: Stand up a GenAI self-service virtual agent | B6: Deflect repetitive contacts and speed resolution with GenAI-assisted self-service. | C6: GenAI virtual agent + digital-workplace portal across tenants; knowledge-grounded responses; agent-assist. | D6: Lifts deflection 12%→35% and improves FCR; part of the core migration scope. | E6: 230000 | F6: 0 | G6: ACCEPTED
A7: Partner-managed operate model (offload platform ops) | B7: The partner runs, patches, upgrades and monitors the ring-fenced platform on the MSP's behalf. | C7: 24×7 managed service; release management; multi-tenant governance; SLA-backed platform availability. | D7: Frees ~3 MSP platform FTEs for billable delivery; predictable managed cost. | E7: 320000 | F7: 0 | G7: ACCEPTED
A8: Phase 2 — add AIOps and Discovery/CMDB | B8: Extend the platform with event correlation, MTTR reduction and CMDB accuracy across tenants. | C8: AIOps (event correlation, noise reduction) + Discovery/CMDB, multi-tenant. | D8: Roadmap expansion once the ITSM core is proven; grows value and partner ARR. | E8: 230000 | F8: 120000 | G8: PROPOSED

Sheet 8. Business case
A1: 8 · Business case
A2: Cost/benefit line items → the app's business case. Finance below mirrors the app's engine (indicative).
A4: Assumptions
A5: Currency
A6: Discount rate | B6: 0.12
A7: Horizon (years) | B7: 5
A9: Cost / benefit line items
A10: Label | B10: Kind | C10: Category | D10: Amount | E10: Year (0=now) | F10: Recurring? | G10: Investment y0 (auto) | H10: Annual benefit (auto) | I10: Annual opex (auto)
A11: Incumbent ITSM licence avoided | B11: BENEFIT | C11: COST_SAVING | D11: 180000 | E11: 0 | F11: Yes | G11: =IF(AND(OR(B11="CAPEX",B11="ONE_OFF"),N(E11)=0),D11,0) | H11: =IF(AND(B11="BENEFIT",F11="Yes"),D11,0) | I11: =IF(OR(B11="OPEX",B11="RECURRING"),D11,0)
A12: Self-hosting & platform-admin effort offloaded to the partner (FTE redeployed to billable) | B12: BENEFIT | C12: COST_SAVING | D12: 320000 | E12: 0 | F12: Yes | G12: =IF(AND(OR(B12="CAPEX",B12="ONE_OFF"),N(E12)=0),D12,0) | H12: =IF(AND(B12="BENEFIT",F12="Yes"),D12,0) | I12: =IF(OR(B12="OPEX",B12="RECURRING"),D12,0)
A13: Analyst productivity — platform automation & GenAI self-service deflection | B13: BENEFIT | C13: TIME_SAVING | D13: 420000 | E13: 0 | F13: Yes | G13: =IF(AND(OR(B13="CAPEX",B13="ONE_OFF"),N(E13)=0),D13,0) | H13: =IF(AND(B13="BENEFIT",F13="Yes"),D13,0) | I13: =IF(OR(B13="OPEX",B13="RECURRING"),D13,0)
A14: SLA penalty / credit avoidance on managed-services contracts | B14: BENEFIT | C14: RISK_REDUCTION | D14: 150000 | E14: 0 | F14: Yes | G14: =IF(AND(OR(B14="CAPEX",B14="ONE_OFF"),N(E14)=0),D14,0) | H14: =IF(AND(B14="BENEFIT",F14="Yes"),D14,0) | I14: =IF(OR(B14="OPEX",B14="RECURRING"),D14,0)
A15: Managed-services revenue protection & tenant growth (differentiated platform) | B15: BENEFIT | C15: REVENUE_UPLIFT | D15: 230000 | E15: 0 | F15: Yes | G15: =IF(AND(OR(B15="CAPEX",B15="ONE_OFF"),N(E15)=0),D15,0) | H15: =IF(AND(B15="BENEFIT",F15="Yes"),D15,0) | I15: =IF(OR(B15="OPEX",B15="RECURRING"),D15,0)
A16: Managed multi-tenant ITSM subscription (ITSM + digital workplace / GenAI) | B16: OPEX | C16: OTHER | D16: 520000 | E16: 0 | F16: Yes | G16: =IF(AND(OR(B16="CAPEX",B16="ONE_OFF"),N(E16)=0),D16,0) | H16: =IF(AND(B16="BENEFIT",F16="Yes"),D16,0) | I16: =IF(OR(B16="OPEX",B16="RECURRING"),D16,0)
A17: Managed-service fee (partner runs & operates the platform) | B17: OPEX | C17: OTHER | D17: 180000 | E17: 0 | F17: Yes | G17: =IF(AND(OR(B17="CAPEX",B17="ONE_OFF"),N(E17)=0),D17,0) | H17: =IF(AND(B17="BENEFIT",F17="Yes"),D17,0) | I17: =IF(OR(B17="OPEX",B17="RECURRING"),D17,0)
A18: Migration & onboarding (build ring-fenced instance, migrate off the incumbent, tenant onboarding, integrations, training) | B18: ONE_OFF | C18: OTHER | D18: 420000 | E18: 0 | F18: No | G18: =IF(AND(OR(B18="CAPEX",B18="ONE_OFF"),N(E18)=0),D18,0) | H18: =IF(AND(B18="BENEFIT",F18="Yes"),D18,0) | I18: =IF(OR(B18="OPEX",B18="RECURRING"),D18,0)
G19: =IF(AND(OR(B19="CAPEX",B19="ONE_OFF"),N(E19)=0),D19,0) | H19: =IF(AND(B19="BENEFIT",F19="Yes"),D19,0) | I19: =IF(OR(B19="OPEX",B19="RECURRING"),D19,0)
G20: =IF(AND(OR(B20="CAPEX",B20="ONE_OFF"),N(E20)=0),D20,0) | H20: =IF(AND(B20="BENEFIT",F20="Yes"),D20,0) | I20: =IF(OR(B20="OPEX",B20="RECURRING"),D20,0)
G21: =IF(AND(OR(B21="CAPEX",B21="ONE_OFF"),N(E21)=0),D21,0) | H21: =IF(AND(B21="BENEFIT",F21="Yes"),D21,0) | I21: =IF(OR(B21="OPEX",B21="RECURRING"),D21,0)
G22: =IF(AND(OR(B22="CAPEX",B22="ONE_OFF"),N(E22)=0),D22,0) | H22: =IF(AND(B22="BENEFIT",F22="Yes"),D22,0) | I22: =IF(OR(B22="OPEX",B22="RECURRING"),D22,0)
G23: =IF(AND(OR(B23="CAPEX",B23="ONE_OFF"),N(E23)=0),D23,0) | H23: =IF(AND(B23="BENEFIT",F23="Yes"),D23,0) | I23: =IF(OR(B23="OPEX",B23="RECURRING"),D23,0)
G24: =IF(AND(OR(B24="CAPEX",B24="ONE_OFF"),N(E24)=0),D24,0) | H24: =IF(AND(B24="BENEFIT",F24="Yes"),D24,0) | I24: =IF(OR(B24="OPEX",B24="RECURRING"),D24,0)
A25: Totals | G25: =SUM(G11:G24) | H25: =SUM(H11:H24) | I25: =SUM(I11:I24)
A27: Results (indicative — the app is the source of truth)
A28: Total investment | B28: =$G$25
A29: Annual net benefit | B29: =$H$25-$I$25
A30: ROI over horizon | B30: =IF($G$25=0,"",($B$29*$B$7-$G$25)/$G$25)
A31: Payback (months) | B31: =IF($B$29<=0,"",$G$25/$B$29*12)
B32: Y0 | C32: Y1 | D32: Y2 | E32: Y3 | F32: Y4 | G32: Y5
A33: Net cash flow by year | B33: =-$G$25 | C33: =IF(1<=$B$7,$B$29,0) | D33: =IF(2<=$B$7,$B$29,0) | E33: =IF(3<=$B$7,$B$29,0) | F33: =IF(4<=$B$7,$B$29,0) | G33: =IF(5<=$B$7,$B$29,0)
A35: NPV @ discount | B35: =B33+NPV($B$6,C33:G33)
A36: IRR | B36: =IFERROR(IRR(B33:G33),"n/a")

Sheet 9. Handover pack
A1: 9 · Handover pack
A2: KPI definitions, baselines, success criteria, expected benefits handed to Value Realization.
A4: KPIs & baselines
A5: KPI (pick) | B5: KPI key (auto) | C5: Baseline | D5: Target | E5: Unit (auto) | F5: Frequency | G5: Data source | H5: Owner
A6: SLA attainment | B6: sla_attainment | C6: 90 | D6: 98 | E6: % | F6: Monthly | G6: Platform dashboards | H6: MSP Service Mgmt
A7: Mean time to resolve (MTTR) | B7: mttr | C7: 7.5 | D7: 4.5 | E7: hours | F7: Monthly | G7: ITSM platform | H7: MSP Operations
A8: Ticket deflection rate | B8: ticket_deflection | C8: 12 | D8: 35 | E8: % | F8: Monthly | G8: Self-service portal | H8: MSP Service Mgmt
A9: First-contact resolution | B9: first_contact_resolution | C9: 58 | D9: 75 | E9: % | F9: Monthly | G9: ITSM platform | H9: Service Desk Lead
B10: =IFERROR(INDEX(Reference!$A$5:$A$34,MATCH(A10,Reference!$B$5:$B$34,0)),"") | E10: =IFERROR(INDEX(Reference!$C$5:$C$34,MATCH(A10,Reference!$B$5:$B$34,0)),"")
B11: =IFERROR(INDEX(Reference!$A$5:$A$34,MATCH(A11,Reference!$B$5:$B$34,0)),"") | E11: =IFERROR(INDEX(Reference!$C$5:$C$34,MATCH(A11,Reference!$B$5:$B$34,0)),"")
B12: =IFERROR(INDEX(Reference!$A$5:$A$34,MATCH(A12,Reference!$B$5:$B$34,0)),"") | E12: =IFERROR(INDEX(Reference!$C$5:$C$34,MATCH(A12,Reference!$B$5:$B$34,0)),"")
B13: =IFERROR(INDEX(Reference!$A$5:$A$34,MATCH(A13,Reference!$B$5:$B$34,0)),"") | E13: =IFERROR(INDEX(Reference!$C$5:$C$34,MATCH(A13,Reference!$B$5:$B$34,0)),"")
B14: =IFERROR(INDEX(Reference!$A$5:$A$34,MATCH(A14,Reference!$B$5:$B$34,0)),"") | E14: =IFERROR(INDEX(Reference!$C$5:$C$34,MATCH(A14,Reference!$B$5:$B$34,0)),"")
B15: =IFERROR(INDEX(Reference!$A$5:$A$34,MATCH(A15,Reference!$B$5:$B$34,0)),"") | E15: =IFERROR(INDEX(Reference!$C$5:$C$34,MATCH(A15,Reference!$B$5:$B$34,0)),"")
A18: Success criteria & expected benefits
A19: Type | B19: Title | C19: Detail | D19: Planned value | E19: Category
A20: EXPECTED_BENEFIT | B20: Net platform value | C20: Net annual value vs the self-managed incumbent | D20: 600000 | E20: COST_SAVING
A21: BASELINE | B21: Incumbent run-rate | C21: Licence + self-hosting/admin ~$500k/yr | D21: 500000 | E21: COST_SAVING
A22: SUCCESS_CRITERION | B22: Zero-disruption cutover | C22: Tenant-by-tenant migration with no SLA breach | D22: 0 | E22: QUALITY
A23: MEASUREMENT_PLAN | B23: Multi-tenant value dashboard | C23: Per-tenant SLA, deflection, MTTR & platform cost tracked monthly | D23: 0 | E23: RELIABILITY

Sheet 10. Risks
A1: 10 · Risk register
A2: Risks to the value case.
A4: Risk / description | B4: Likelihood (1–5) | C4: Impact (1–5) | D4: Score (auto) | E4: Mitigation | F4: Status
A5: Tenant data-migration complexity (incumbent → new platform, per-tenant isolation) | B5: 3 | C5: 4 | D5: =IFERROR(B5*C5,"") | E5: Phased tenant-by-tenant migration; ETL; parallel run; partner-led | F5: OPEN
A6: Cross-tenant data exposure via multi-tenancy misconfiguration (data-residency / sovereignty) | B6: 2 | C6: 5 | D6: =IFERROR(B6*C6,"") | E6: Ring-fenced instance; strict tenant isolation; partner-managed; data-residency controls | F6: OPEN
A7: SLA disruption during cutover on live managed-services contracts | B7: 2 | C7: 4 | D7: =IFERROR(B7*C7,"") | E7: Tenant-by-tenant cutover, parallel run, rollback; SLA monitoring | F7: OPEN
A8: Higher recurring cost vs the incumbent not offset by realised productivity | B8: 3 | C8: 3 | D8: =IFERROR(B8*C8,"") | E8: Track productivity & FTE-offload benefits quarterly on the value dashboard | F8: OPEN
A9: Analyst adoption / change vs the familiar incumbent UI | B9: 3 | C9: 3 | D9: =IFERROR(B9*C9,"") | E9: GenAI virtual agent + digital-workplace UX; training; champion network | F9: OPEN
A10: Integration rebuild (directory/SSO, email, monitoring) slips | B10: 3 | C10: 3 | D10: =IFERROR(B10*C10,"") | E10: Prioritise top integrations; iPaaS/REST; phased | F10: OPEN
D11: =IFERROR(B11*C11,"")
D12: =IFERROR(B12*C12,"")
D13: =IFERROR(B13*C13,"")
D14: =IFERROR(B14*C14,"")
D15: =IFERROR(B15*C15,"")
D16: =IFERROR(B16*C16,"")
D17: =IFERROR(B17*C17,"")
