Workbook
Name SolutionProfiles: '_Lists'!$A$2:$A$5
Name StudyTypes: _Lists!$B$2:$B$20
Name CostItemKind: '_Lists'!$C$2:$C$6
Name BenefitCategory: '_Lists'!$D$2:$D$9
Name FunctionKind: '_Lists'!$E$2:$E$3
Name RecommendationStatus: '_Lists'!$F$2:$F$6
Name YesNo: '_Lists'!$G$2:$G$3
Name Currencies: '_Lists'!$H$2:$H$9
Name KpiNames: '_Lists'!$I$2:$I$31
Name WorkPackageStatus: '_Lists'!$J$2:$J$5
Name RiskStatus: '_Lists'!$K$2:$K$5
Name Health: '_Lists'!$L$2:$L$4
Name Confidence: '_Lists'!$M$2:$M$4
Name Scale: '_Lists'!$N$2:$N$6
Name TrackOrigin: '_Lists'!$O$2:$O$3
Name ArtifactType: '_Lists'!$P$2:$P$6
Name LessonCat: '_Lists'!$Q$2:$Q$4

Sheet Read me
A1: Value Lifecycle · VR Intake Workbook — Read me
A2: How to use this workbook, and how each tab maps to the Value Lifecycle Platform.
A5: Purpose | B5: Capture what you learn in client meetings, then transcribe into the app — or import this whole file.
A6: Colour key | B6: Yellow cells = you fill in. Grey cells = auto-calculated (don't type over them). Header rows = fixed.
A7: Dropdowns | B7: Cells with a dropdown use the app's own pick-lists (solution profiles, study types, KPIs, currencies, statuses) so entries match the system.
A8: Example row | B8: The first data row of each table is a greyed-italic EXAMPLE of the format — overwrite it or delete it.
A9: Provenance | B9: Wherever you record a number, capture its Source / Period / Assumption / Confidence.
A10: Importing | B10: A study/track can be loaded straight from this file: npx tsx scripts/import-workbook.ts <file>.xlsx (add --dry-run to preview).
A11: Before you import | B11: Delete the greyed example row in each table (or add rows beneath it); keep the tab names and column headers unchanged.
A13: Tab → App module
A14: 1. Track | B14: Realization track header (origin, objectives, planned value)
A15: 2. Baselines | B15: Validate/establish KPI baselines
A16: 3. Work packages | B16: Work packages
A17: 4. Adoption plan | B17: Adoption plan activities
A18: 5. KPI tracker | B18: KPI targets + actuals by period
A19: 6. Benefits | B19: Benefits — planned vs realized
A20: 7. Risks & issues | B20: Track risk/issue register
A21: 8. QBR notes | B21: Quarterly value review notes
A22: 9. Lessons | B22: Lessons learned
A23: Reference | B23: KPI catalogue + per-profile drivers & levers

Sheet Reference
A1: Reference — KPI catalogue & profile prompts
A2: Pick-list prompts from the app. Use these to fill the dropdowns and shape the conversation.
A4: KPI key | B4: KPI name | C4: Unit | D4: Direction | E4: Discipline | F4: Category
A5: cost_savings | B5: Estimated / realized cost savings | C5: USD | D5: HIGHER_IS_BETTER | E5: VE | F5: COST_SAVING
A6: roi_pct | B6: Return on investment | C6: % | D6: HIGHER_IS_BETTER | E6: VE | F6: COST_SAVING
A7: payback_period | B7: Payback period | C7: months | D7: LOWER_IS_BETTER | E7: VE | F7: COST_SAVING
A8: revenue_uplift | B8: Revenue uplift | C8: USD | D8: HIGHER_IS_BETTER | E8: VR | F8: REVENUE_UPLIFT
A9: alternatives_generated | B9: Alternatives generated | C9: count | D9: HIGHER_IS_BETTER | E9: VE | F9: OTHER
A10: recommendations_accepted | B10: Recommendations accepted | C10: count | D10: HIGHER_IS_BETTER | E10: VE | F10: OTHER
A11: study_cycle_time | B11: Study cycle time | C11: days | D11: LOWER_IS_BETTER | E11: VE | F11: TIME_SAVING
A12: avg_roi | B12: Average ROI per study | C12: % | D12: HIGHER_IS_BETTER | E12: VE | F12: COST_SAVING
A13: on_time_implementation | B13: On-time implementation | C13: % | D13: HIGHER_IS_BETTER | E13: VR | F13: SCHEDULE
A14: adoption_rate | B14: Adoption rate | C14: % | D14: HIGHER_IS_BETTER | E14: VR | F14: OTHER
A15: task_utilization | B15: Licence / capacity utilization | C15: % | D15: HIGHER_IS_BETTER | E15: VR | F15: COST_SAVING
... A34: first_contact_resolution | B34: First-contact resolution | C34: % | D34: HIGHER_IS_BETTER | E34: VR | F34: QUALITY

Sheet _Lists
A1: SolutionProfiles | B1: StudyTypes | C1: CostItemKind | D1: BenefitCategory | E1: FunctionKind | F1: RecommendationStatus | G1: YesNo | H1: Currencies | I1: KpiNames | J1: WorkPackageStatus | K1: RiskStatus | L1: Health | M1: Confidence | N1: Scale | O1: TrackOrigin | P1: ArtifactType | Q1: LessonCat
A2: automation | B2: Adoption & value-realization study | C2: CAPEX | D2: COST_SAVING | E2: BASIC | F2: PROPOSED | G2: Yes | H2: USD | I2: Estimated / realized cost savings | J2: NOT_STARTED | K2: OPEN | L2: GREEN | M2: High | N2: 1 | O2: STANDALONE (existing software) | P2: EXPECTED_BENEFIT | Q2: what_worked
A3: mainframe | B3: Automation value study | C3: OPEX | D3: REVENUE_UPLIFT | E3: SECONDARY | F3: SHORTLISTED | G3: No | H3: ZAR | I3: Return on investment | J3: IN_PROGRESS | K3: MITIGATING | L3: AMBER | M3: Medium | N3: 2 | O3: VE_HANDOVER (from a study) | P3: SUCCESS_CRITERION | Q3: what_to_change
A4: serviceops | B4: Availability & resilience review | C4: ONE_OFF | D4: RISK_REDUCTION | F4: ACCEPTED | H4: EUR | I4: Payback period | J4: BLOCKED | K4: CLOSED | L4: RED | M4: Low | N4: 3 | P4: BASELINE | Q4: recommendation_for_ve
A5: reseller | B5: Build-vs-buy business case | C5: RECURRING | D5: TIME_SAVING | F5: REJECTED | H5: GBP | I5: Revenue uplift | J5: DONE | K5: ACCEPTED | N5: 4 | P5: KPI
B6: Capacity & cost forecasting study | C6: BENEFIT | D6: QUALITY | F6: DEFERRED | H6: AUD | I6: Alternatives generated | N6: 5 | P6: RISK
B7: Cloud migration / modernization TCO case | D7: SCHEDULE | H7: NGN | I7: Recommendations accepted
B8: Competitive displacement / TCO case | D8: RELIABILITY | H8: KES | I8: Study cycle time
B9: Consolidation case (tool / licence) | D9: OTHER | H9: BWP | I9: Average ROI per study
B10: Continuous optimization / cost case | I10: On-time implementation
B11: Cost-optimization study | I11: Adoption rate
B12: ITSM value / TCO study | I12: Licence / capacity utilization
B13: Managed-service (MSP) migration case | I13: Time-to-value
B14: Proof-of-value (PoV) outcome study | I14: Developer productivity
B15: Renewal & expansion case | I15: New-developer onboarding time
B16: ROI / TCO business case | I16: Realized value
B17: SaaS migration case | I17: Planned vs realized variance
B18: Security & compliance risk-reduction case | I18: Value reports / QBRs delivered
B19: Self-service deflection study | I19: Total realized value (portfolio)
B20: Value realisation & optimisation study | I20: Template / plan reuse rate
I21: Schedule impact
I22: Life-cycle cost reduction
I23: Reliability / uptime
I24: Unit cost reduction
I25: First pass yield
I26: Mainframe cost reduction (MLC / MSU)
I27: Mean time to resolve (MTTR)
I28: Job success rate
I29: SLA attainment
I30: Ticket deflection rate
I31: First-contact resolution

Sheet 1. Track
A1: 1 · Track
A2: Realization track header → maps to the app's New realization track (or the VE → VR handover).
A4: Client / account
A5: Track title | B5: ITSM Platform Displacement — Value Realization
A6: Origin | B6: Handover from VE study
A7: Source study code (if handover)
A8: Solution profile | B8: serviceops
A9: VRM (owner)
A10: Objectives | B10: Realise the displacement business case: stand up the target platform, migrate off the incumbent, and prove the ~$630K/yr net platform saving while improving MTTR, deflection and SLA.
A11: Success criteria | B11: Incumbent fully decommissioned on plan; net annual TCO saving ≥ $630K evidenced; MTTR ≤ 4.0h; deflection ≥ 35%; zero consumption / true-up overages post-cutover.
A12: Planned value | B12: 630000
A13: Currency | B13: USD
A14: Start date | B14: 2027-01-15
A15: Target date | B15: 2027-12-31

Sheet 2. Baselines
A1: 2 · Baseline & measurement
A2: Validate baselines (handover) or establish them from the live deployment (standalone).
A4: KPI (pick) | B4: KPI key (auto) | C4: Baseline value | D4: Unit (auto) | E4: Data source | F4: Frequency | G4: Owner | H4: Validated / established?
A5: Mean time to resolve (MTTR) | B5: mttr | C5: 6.5 | D5: hours | E5: Incumbent ITSM reports | F5: Monthly | G5: IT Operations | H5: yes
A6: SLA attainment | B6: sla_attainment | C6: 92 | D6: % | E6: Incumbent SLA reports | F6: Monthly | G6: Service Owner | H6: yes
A7: Ticket deflection rate | B7: ticket_deflection | C7: 18 | D7: % | E7: Portal analytics | F7: Monthly | G7: Service Owner | H7: yes
A8: First-contact resolution | B8: first_contact_resolution | C8: 61 | D8: % | E8: ITSM | F8: Monthly | G8: Service Desk Lead | H8: yes
B9: =IFERROR(INDEX(Reference!$A$5:$A$34,MATCH(A9,Reference!$B$5:$B$34,0)),"") | D9: =IFERROR(INDEX(Reference!$C$5:$C$34,MATCH(A9,Reference!$B$5:$B$34,0)),"")
B10: =IFERROR(INDEX(Reference!$A$5:$A$34,MATCH(A10,Reference!$B$5:$B$34,0)),"") | D10: =IFERROR(INDEX(Reference!$C$5:$C$34,MATCH(A10,Reference!$B$5:$B$34,0)),"")
B11: =IFERROR(INDEX(Reference!$A$5:$A$34,MATCH(A11,Reference!$B$5:$B$34,0)),"") | D11: =IFERROR(INDEX(Reference!$C$5:$C$34,MATCH(A11,Reference!$B$5:$B$34,0)),"")
B12: =IFERROR(INDEX(Reference!$A$5:$A$34,MATCH(A12,Reference!$B$5:$B$34,0)),"") | D12: =IFERROR(INDEX(Reference!$C$5:$C$34,MATCH(A12,Reference!$B$5:$B$34,0)),"")
B13: =IFERROR(INDEX(Reference!$A$5:$A$34,MATCH(A13,Reference!$B$5:$B$34,0)),"") | D13: =IFERROR(INDEX(Reference!$C$5:$C$34,MATCH(A13,Reference!$B$5:$B$34,0)),"")
B14: =IFERROR(INDEX(Reference!$A$5:$A$34,MATCH(A14,Reference!$B$5:$B$34,0)),"") | D14: =IFERROR(INDEX(Reference!$C$5:$C$34,MATCH(A14,Reference!$B$5:$B$34,0)),"")
B15: =IFERROR(INDEX(Reference!$A$5:$A$34,MATCH(A15,Reference!$B$5:$B$34,0)),"") | D15: =IFERROR(INDEX(Reference!$C$5:$C$34,MATCH(A15,Reference!$B$5:$B$34,0)),"")
B16: =IFERROR(INDEX(Reference!$A$5:$A$34,MATCH(A16,Reference!$B$5:$B$34,0)),"") | D16: =IFERROR(INDEX(Reference!$C$5:$C$34,MATCH(A16,Reference!$B$5:$B$34,0)),"")

Sheet 3. Work packages
A1: 3 · Work packages
A2: From accepted recommendations, or defined directly for a standalone track.
A4: Name | B4: Description | C4: Owner | D4: Start | E4: Due | F4: Status
A5: Stand up target platform (Kubernetes, in-country) | B5: Deploy ITSM + AIOps on private cloud for data residency | C5: Platform Engineering | D5: 2027-01-15 | E5: 2027-03-15 | F5: IN_PROGRESS
A6: Migrate CMDB & discovery (200k–800k items) | B6: ETL + discovery re-baseline; index tuning for large item loads | C6: CMDB Lead | D6: 2027-02-01 | E6: 2027-05-15 | F6: NOT_STARTED
A7: Migrate ITSM processes (incident/request/change/problem) | B7: Configure workflows; parallel run against the incumbent | C7: ITSM Lead | D7: 2027-03-01 | E7: 2027-06-30 | F7: NOT_STARTED
A8: Rebuild priority integrations (iPaaS / REST) | B8: Top 10 integrations first; retire incumbent connectors | C8: Integration Lead | D8: 2027-03-15 | E8: 2027-06-30 | F8: NOT_STARTED
A9: Cutover & decommission incumbent | B9: Domain-by-domain cutover aligned to renewal; contract exit | C9: Programme Manager | D9: 2027-07-01 | E9: 2027-09-30 | F9: NOT_STARTED

Sheet 4. Adoption plan
A1: 4 · Adoption plan
A2: Who's impacted, training, comms, champions — value comes from use.
A4: Activity | B4: Audience / who's impacted | C4: Owner | D4: Due | E4: Status
A5: GenAI-assistant + modern-workplace training | B5: All fulfillers & end users | C5: Enablement | D5: 2027-04-15 | E5: NOT_STARTED
A6: Champion network across service teams | B6: Team leads | C6: Service Owner | D6: 2027-04-01 | E6: IN_PROGRESS
A7: Self-service / virtual-agent adoption push | B7: End users | C7: Comms | D7: 2027-05-01 | E7: NOT_STARTED

Sheet 5. KPI tracker
A1: 5 · KPI tracker
A2: Targets + actuals by period. Attainment auto-calcs vs baseline → target.
A4: KPI (pick) | B4: KPI key (auto) | C4: Baseline | D4: Target | E4: Unit (auto) | F4: Period | G4: Actual | H4: Attainment % (auto)
A5: Mean time to resolve (MTTR) | B5: mttr | C5: 6.5 | D5: 4 | E5: hours | F5: 2027-03-31 | G5: 5.6 | H5: =IFERROR((G5-C5)/(D5-C5),"")
A6: Mean time to resolve (MTTR) | B6: mttr | C6: 6.5 | D6: 4 | E6: hours | F6: 2027-06-30 | G6: 4.9 | H6: =IFERROR((G6-C6)/(D6-C6),"")
A7: Ticket deflection rate | B7: ticket_deflection | C7: 18 | D7: 35 | E7: % | F7: 2027-03-31 | G7: 24 | H7: =IFERROR((G7-C7)/(D7-C7),"")
A8: Ticket deflection rate | B8: ticket_deflection | C8: 18 | D8: 35 | E8: % | F8: 2027-06-30 | G8: 29 | H8: =IFERROR((G8-C8)/(D8-C8),"")
A9: SLA attainment | B9: sla_attainment | C9: 92 | D9: 98 | E9: % | F9: 2027-06-30 | G9: 95 | H9: =IFERROR((G9-C9)/(D9-C9),"")
A10: First-contact resolution | B10: first_contact_resolution | C10: 61 | D10: 75 | E10: % | F10: 2027-06-30 | G10: 67 | H10: =IFERROR((G10-C10)/(D10-C10),"")
B11: =IFERROR(INDEX(Reference!$A$5:$A$34,MATCH(A11,Reference!$B$5:$B$34,0)),"") | E11: =IFERROR(INDEX(Reference!$C$5:$C$34,MATCH(A11,Reference!$B$5:$B$34,0)),"") | H11: =IFERROR((G11-C11)/(D11-C11),"")
B12: =IFERROR(INDEX(Reference!$A$5:$A$34,MATCH(A12,Reference!$B$5:$B$34,0)),"") | E12: =IFERROR(INDEX(Reference!$C$5:$C$34,MATCH(A12,Reference!$B$5:$B$34,0)),"") | H12: =IFERROR((G12-C12)/(D12-C12),"")
B13: =IFERROR(INDEX(Reference!$A$5:$A$34,MATCH(A13,Reference!$B$5:$B$34,0)),"") | E13: =IFERROR(INDEX(Reference!$C$5:$C$34,MATCH(A13,Reference!$B$5:$B$34,0)),"") | H13: =IFERROR((G13-C13)/(D13-C13),"")
B14: =IFERROR(INDEX(Reference!$A$5:$A$34,MATCH(A14,Reference!$B$5:$B$34,0)),"") | E14: =IFERROR(INDEX(Reference!$C$5:$C$34,MATCH(A14,Reference!$B$5:$B$34,0)),"") | H14: =IFERROR((G14-C14)/(D14-C14),"")
B15: =IFERROR(INDEX(Reference!$A$5:$A$34,MATCH(A15,Reference!$B$5:$B$34,0)),"") | E15: =IFERROR(INDEX(Reference!$C$5:$C$34,MATCH(A15,Reference!$B$5:$B$34,0)),"") | H15: =IFERROR((G15-C15)/(D15-C15),"")
B16: =IFERROR(INDEX(Reference!$A$5:$A$34,MATCH(A16,Reference!$B$5:$B$34,0)),"") | E16: =IFERROR(INDEX(Reference!$C$5:$C$34,MATCH(A16,Reference!$B$5:$B$34,0)),"") | H16: =IFERROR((G16-C16)/(D16-C16),"")
B17: =IFERROR(INDEX(Reference!$A$5:$A$34,MATCH(A17,Reference!$B$5:$B$34,0)),"") | E17: =IFERROR(INDEX(Reference!$C$5:$C$34,MATCH(A17,Reference!$B$5:$B$34,0)),"") | H17: =IFERROR((G17-C17)/(D17-C17),"")
B18: =IFERROR(INDEX(Reference!$A$5:$A$34,MATCH(A18,Reference!$B$5:$B$34,0)),"") | E18: =IFERROR(INDEX(Reference!$C$5:$C$34,MATCH(A18,Reference!$B$5:$B$34,0)),"") | H18: =IFERROR((G18-C18)/(D18-C18),"")
B19: =IFERROR(INDEX(Reference!$A$5:$A$34,MATCH(A19,Reference!$B$5:$B$34,0)),"") | E19: =IFERROR(INDEX(Reference!$C$5:$C$34,MATCH(A19,Reference!$B$5:$B$34,0)),"") | H19: =IFERROR((G19-C19)/(D19-C19),"")

Sheet 6. Benefits
A1: 6 · Benefits — planned vs realized
A2: Realized rolls up to the track & portfolio in the app.
A4: Benefit | B4: Category | C4: Planned value | D4: Realized value | E4: Variance (auto)
A5: Platform TCO reduction vs the incumbent (net, annualised) | B5: COST_SAVING | C5: 630000 | D5: 160000 | E5: =IFERROR(D5-C5,"")
A6: Eliminated consumption / true-up surprises | B6: RISK_REDUCTION | C6: 0 | D6: 0 | E6: =IFERROR(D6-C6,"")
E7: =IFERROR(D7-C7,"")
E8: =IFERROR(D8-C8,"")
E9: =IFERROR(D9-C9,"")
E10: =IFERROR(D10-C10,"")
E11: =IFERROR(D11-C11,"")
E12: =IFERROR(D12-C12,"")
E13: =IFERROR(D13-C13,"")
E14: =IFERROR(D14-C14,"")
E15: =IFERROR(D15-C15,"")
E16: =IFERROR(D16-C16,"")
E17: =IFERROR(D17-C17,"")

Sheet 7. Risks & issues
A1: 7 · Risks & issues
A2: Risks to realizing value.
A4: Risk / issue | B4: Likelihood (1–5) | C4: Impact (1–5) | D4: Score (auto) | E4: Mitigation | F4: Status
A5: CMDB migration index performance on large item loads | B5: 3 | C5: 3 | D5: =IFERROR(B5*C5,"") | E5: Index tuning; batch loads; discovery re-baseline | F5: OPEN
A6: Integration rebuild backlog slows cutover | B6: 3 | C6: 3 | D6: =IFERROR(B6*C6,"") | E6: Prioritise top-10 integrations; iPaaS first | F6: OPEN
A7: Adoption lag vs the familiar incumbent UI | B7: 2 | C7: 3 | D7: =IFERROR(B7*C7,"") | E7: GenAI assistant UX; champions; training | F7: MITIGATING
A8: Incumbent decommission slips past renewal date | B8: 2 | C8: 4 | D8: =IFERROR(B8*C8,"") | E8: Domain-by-domain cutover; procurement-led exit plan | F8: OPEN
D9: =IFERROR(B9*C9,"")
D10: =IFERROR(B10*C10,"")
D11: =IFERROR(B11*C11,"")
D12: =IFERROR(B12*C12,"")
D13: =IFERROR(B13*C13,"")
D14: =IFERROR(B14*C14,"")
D15: =IFERROR(B15*C15,"")
D16: =IFERROR(B16*C16,"")
D17: =IFERROR(B17*C17,"")

Sheet 8. QBR notes
A1: 8 · QBR / value review notes
A2: Reconcile realized value vs the business case.
A4: Review date
A5: Attendees
A6: Realized vs planned (summary) | B6: One quarter into realization ~$160K of the $630K annual net saving is banked (incumbent operations-mgmt & AI consumption already off the bill). MTTR down 6.5→4.9h and deflection 18→29% as AIOps and the GenAI assistant come online.
A7: Wins | B7: GenAI assistant live; AIOps cut alert noise ~95%; first two service domains cut over; no consumption overages since migration started.
A8: Risks / blockers | B8: CMDB migration index performance and the integration-rebuild backlog are the critical path to full decommission.
A9: Renewal / expansion signal | B9: Incumbent renewal exit on track; strong signal to extend the platform to security operations and HR service delivery later.
A10: Actions & owners | B10: Finish CMDB cutover — CMDB Lead; prioritise top-10 integrations — Integration Lead; book executive QBR — CSM

Sheet 9. Lessons
A1: 9 · Lessons learned
A2: Feed improvements back into the VE templates & playbooks.
A4: Category | B4: Lesson | C4: Recommendation for next time
A5: what_worked | B5: Coexistence dual-run removed cutover risk and protected SLAs | C5: Reuse the phased, domain-by-domain displacement playbook
A6: watch_out | B6: Integration rebuild took longer than the licence migration itself | C6: Start iPaaS/REST integration mapping in week 1, before ITSM config
